quartutils/__init__.py
quartutils/task_server.py
quartutils/test_task_server.py
quartutils/worker_class.py
quartutils-0.0.1.dist-info/LICENSE
quartutils-0.0.1.dist-info/METADATA
quartutils-0.0.1.dist-info/WHEEL
quartutils-0.0.1.dist-info/top_level.txt
quartutils-0.0.1.dist-info/RECORD
